pyhabitat/__init__.py
pyhabitat/__main__.py
pyhabitat/cli.py
pyhabitat/demo.py
pyhabitat/environment.py
pyhabitat/reporting.py
pyhabitat/system_info.py
pyhabitat/version_info.py
pyhabitat-1.1.5.dist-info/licenses/LICENSE
pyhabitat-1.1.5.dist-info/METADATA
pyhabitat-1.1.5.dist-info/WHEEL
pyhabitat-1.1.5.dist-info/entry_points.txt
pyhabitat-1.1.5.dist-info/top_level.txt
pyhabitat-1.1.5.dist-info/RECORD
