Metadata-Version: 2.4
Name: pyhabitat
Version: 1.1.5
Summary: A lightweight library for detecting system environment, GUI, and build properties.
Author-email: George Clayton Bennett <george.bennett@memphistn.gov>
Maintainer-email: George Clayton Bennett <george.bennett@memphistn.gov>
License-Expression: MIT
Keywords: environment,os-detection,build-system
Classifier: Programming Language :: Python :: 3
Classifier: Operating System :: OS Independent
Classifier: Intended Audience :: Developers
Classifier: Environment :: Console
Classifier: Topic :: Software Development :: Build Tools
Classifier: Topic :: Software Development :: Libraries :: Python Modules
Classifier: Topic :: Utilities
Requires-Python: >=3.7
License-File: LICENSE
Dynamic: license-file
